yleisavain/__init__.py
yleisavain/esilataus.py
django_yleisavain-0.2.dist-info/METADATA
django_yleisavain-0.2.dist-info/WHEEL
django_yleisavain-0.2.dist-info/historia.json
django_yleisavain-0.2.dist-info/top_level.txt
django_yleisavain-0.2.dist-info/RECORD
